CHANGES.txt
LICENSE.txt
MANIFEST.in
README.rst
ROADMAP.txt
notes.txt
setup.py
ConsoleServer.egg-info/PKG-INFO
ConsoleServer.egg-info/SOURCES.txt
ConsoleServer.egg-info/dependency_links.txt
ConsoleServer.egg-info/entry_points.txt
ConsoleServer.egg-info/requires.txt
ConsoleServer.egg-info/top_level.txt
consoleserver/__init__.py
consoleserver/config.ini
consoleserver/config.py
consoleserver/consolecollection.py
consoleserver/consolehandler.py
consoleserver/consoleserver.py
consoleserver/logging.ini
consoleserver/main.py
consoleserver/monitoredconsolecollection.py
consoleserver/ssh.py
consoleserver/ssh_protocol.py
etc/init.d/consoleserver
etc/logrotate.d/consoleserver
etc/udev/rules.d/99-usb-blacklist.rules