Metadata-Version: 1.1
Name: ConsoleServer
Version: 1.0.2
Summary: This is a logging console server that can also be accessed over ssh.
Home-page: https://github.com/LawrenceK/console-server
Author: Lawrence P. Klyne
Author-email: pypi@lklyne.co.uk
License: GPL
Keywords: console,server,ssh,serial
Platform: UNKNOWN
Classifier: Development Status :: 4 - Beta
Classifier: Operating System :: POSIX :: Linux
Classifier: Programming Language :: Python
